{
  "title": "Recent posts",
  "items": [
    {
      "title": "使用 github.io 和 Docusaurus 搭建个人博客网站",
      "permalink": "/blog/githubio-blog-with-docusaurus",
      "unlisted": false
    },
    {
      "title": "Welcome",
      "permalink": "/blog/welcome",
      "unlisted": false
    },
    {
      "title": "MDX Blog Post",
      "permalink": "/blog/mdx-blog-post",
      "unlisted": false
    },
    {
      "title": "Long Blog Post",
      "permalink": "/blog/long-blog-post",
      "unlisted": false
    },
    {
      "title": "First Blog Post",
      "permalink": "/blog/first-blog-post",
      "unlisted": false
    }
  ]
}